{
  "azurirano": "2026-06-19T18:51:38.305153+00:00",
  "azurirano_sr": "19. 06. 2026. у 20:51",
  "vesti_24h": 10,
  "vesti": [
    {
      "naslov": "Montela zarežao na Turke da mu se skinu sa grbače: Pregrubi ste - mi smo ljudi, ne roboti",
      "url": "https://www.mozzartsport.com/fudbal/vesti/montela-zarezao-na-turke-da-mu-se-skinu-sa-grbace-pregrubi-ste-mi-smo-ljudi-ne-roboti/546816",
      "izvor": "Мозарт Спорт",
      "datum": "19. 06. 2026. у 17:42",
      "slika": null
    },
    {
      "naslov": "Humanitarni tiket u podne: Mundijalski tipovi Marjana Markovića za dobitnih 200.000 dinara",
      "url": "https://www.mozzartsport.com/fudbal/vesti/humanitarni-tiket-u-podne-mundijalski-tipovi-marjana-markovica-za-dobitnih-200000-dinara/546795",
      "izvor": "Мозарт Спорт",
      "datum": "19. 06. 2026. у 14:20",
      "slika": null
    },
    {
      "naslov": "Zemun sklapa tim za Superligu: Belaković pojačao krilo, bonus stigao iz Priboja",
      "url": "https://www.mozzartsport.com/fudbal/vesti/zemun-sklapa-tim-za-superligu-belakovic-pojacao-krilo-bonus-stigao-iz-priboja/546791",
      "izvor": "Мозарт Спорт",
      "datum": "19. 06. 2026. у 14:13",
      "slika": null
    },
    {
      "naslov": "Sokermanija u Sijetlu: „Gnezdo” će da gori, još samo Pulišić da se oporavi",
      "url": "https://www.mozzartsport.com/fudbal/vesti/sokermanija-u-sijetlu-gnezdo-ce-da-gori-jos-samo-pulisic-da-se-oporavi/546769",
      "izvor": "Мозарт Спорт",
      "datum": "19. 06. 2026. у 11:40",
      "slika": null
    },
    {
      "naslov": "Premijer liga počinje 21. avgusta, Arsenal u prvom kolu dočekuje Konventri",
      "url": "https://www.tanjug.rs/sport/fudbal/260474/premijer-liga-pocinje-21-avgusta-arsenal-u-prvom-kolu-docekuje-konventri/vest",
      "izvor": "Танјуг",
      "datum": "19. 06. 2026. у 15:08",
      "slika": null
    },
    {
      "naslov": "Fudbaleri Crvene zvezde pobedili Jedinstvo iz Užica u prijateljskoj utakmici",
      "url": "https://www.tanjug.rs/sport/fudbal/260458/fudbaleri-crvene-zvezde-pobedili-jedinstvo-iz-uzica-u-prijateljskoj-utakmici/vest",
      "izvor": "Танјуг",
      "datum": "19. 06. 2026. у 13:49",
      "slika": null
    },
    {
      "naslov": "Kristijan Kivu produžio ugovor sa Interom do 2028. godine",
      "url": "https://www.tanjug.rs/sport/fudbal/260417/kristijan-kivu-produzio-ugovor-sa-interom-do-2028-godine/vest",
      "izvor": "Танјуг",
      "datum": "19. 06. 2026. у 11:39",
      "slika": null
    },
    {
      "naslov": "Holandski fudbaler Jan Pol van Heke prešao iz Brajtona u Totenhem",
      "url": "https://www.tanjug.rs/sport/fudbal/260411/holandski-fudbaler-jan-pol-van-heke-presao-iz-brajtona-u-totenhem/vest",
      "izvor": "Танјуг",
      "datum": "19. 06. 2026. у 11:29",
      "slika": null
    },
    {
      "naslov": "Popović i Vidojević produžili saradnju sa Pančevcima",
      "url": "https://www.b92.net/sport/fudbal/srpski-fudbal/243474/zeleznicar-produzio-ugovor-sa-popovicem/vest",
      "izvor": "Б92 Српски фудбал",
      "datum": "19. 06. 2026. у 19:31",
      "slika": null
    },
    {
      "naslov": "Čukarički zadržao Miladinovića",
      "url": "https://www.b92.net/sport/fudbal/srpski-fudbal/243460/uros-miladinovic-ostaje-u-cukarickom/vest",
      "izvor": "Б92 Српски фудбал",
      "datum": "19. 06. 2026. у 18:25",
      "slika": null
    }
  ]
}