{
  "azurirano": "2026-05-07T06:47:03.887973+00:00",
  "azurirano_sr": "7. 05. 2026. у 08:47",
  "vesti_24h": 10,
  "vesti": [
    {
      "naslov": "NAJAVA DANA (četvrtak, 7. maj): Liga Evrope, Liga konferencije i Mozzart Bet PLS naravno",
      "url": "https://www.mozzartsport.com/fudbal/vesti/najava-dana-cetvrtak-7-maj-liga-evrope-liga-konferencije-i-mozzart-bet-pls-naravno/543086",
      "izvor": "Мозарт Спорт",
      "datum": "7. 05. 2026. у 10:16",
      "slika": null
    },
    {
      "naslov": "In memoriam: Vladimir Cvetković",
      "url": "https://www.mozzartsport.com/fudbal/vesti/in-memoriam-vladimir-cvetkovic/543114",
      "izvor": "Мозарт Спорт",
      "datum": "6. 05. 2026. у 22:39",
      "slika": null
    },
    {
      "naslov": "KRAJ -  Liga šampiona: Bajern - Pari Sen Žermen 1:1",
      "url": "https://www.mozzartsport.com/fudbal/vesti/kraj-liga-sampiona-bajern-pari-sen-zermen-11/543109",
      "izvor": "Мозарт Спорт",
      "datum": "6. 05. 2026. у 21:57",
      "slika": null
    },
    {
      "naslov": "Pre Terzića je bio Srbin sa cigarom i hteo je da se fudbaleri bave atletikom",
      "url": "https://www.mozzartsport.com/fudbal/vesti/pre-terzica-je-bio-srbin-sa-cigarom-i-hteo-je-da-se-fudbaleri-bave-atletikom/543098",
      "izvor": "Мозарт Спорт",
      "datum": "6. 05. 2026. у 20:10",
      "slika": null
    },
    {
      "naslov": "Remi u Minhenu, fudbaleri Pari Sen Žermena u finalu Lige šampiona",
      "url": "https://www.tanjug.rs/sport/fudbal/250091/remi-u-minhenu-fudbaleri-pari-sen-zermena-u-finalu-lige-sampiona/vest",
      "izvor": "Танјуг",
      "datum": "6. 05. 2026. у 23:14",
      "slika": null
    },
    {
      "naslov": "Fudbalski savez Srbije izrazio saučešće povodom smrti Vladimira Cvetkovića",
      "url": "https://www.tanjug.rs/sport/fudbal/250081/fudbalski-savez-srbije-izrazio-saucesce-povodom-smrti-vladimira-cvetkovica/vest",
      "izvor": "Танјуг",
      "datum": "6. 05. 2026. у 22:11",
      "slika": null
    },
    {
      "naslov": "FIFA uvela globalnu suspenziju za argentinskog fudbalera Đanluku Prestijanija",
      "url": "https://www.tanjug.rs/sport/fudbal/250078/fifa-uvela-globalnu-suspenziju-za-argentinskog-fudbalera-danluku-prestijanija/vest",
      "izvor": "Танјуг",
      "datum": "6. 05. 2026. у 21:54",
      "slika": null
    },
    {
      "naslov": "Vaterpolisti Novog Beograda pobedili Šabac i plasirali se u finale plej-ofa SLS",
      "url": "https://www.tanjug.rs/sport/fudbal/250074/vaterpolisti-novog-beograda-pobedili-sabac-i-plasirali-se-u-finale-plej-ofa-sls/vest",
      "izvor": "Танјуг",
      "datum": "6. 05. 2026. у 21:39",
      "slika": null
    },
    {
      "naslov": "Džajić se oprostio od Cvetkovića: &quot;Zajedno smo sanjali velike snove&quot;",
      "url": "https://www.b92.net/sport/fudbal/srpski-fudbal/231266/dzajic-se-oprostio-od-cvetkovica-zajedno-smo-sanjali-velike-snove/vest",
      "izvor": "Б92 Српски фудбал",
      "datum": "7. 05. 2026. у 08:30",
      "slika": null
    },
    {
      "naslov": "Superliga u svetskom vrhu – po smeni trenera",
      "url": "https://www.b92.net/sport/fudbal/srpski-fudbal/231143/superliga-osma-na-svetu-po-broju-smenjenih-trenera/vest",
      "izvor": "Б92 Српски фудбал",
      "datum": "6. 05. 2026. у 22:24",
      "slika": null
    }
  ]
}