{
  "azurirano": "2026-06-28T04:51:51.455002+00:00",
  "azurirano_sr": "28. 06. 2026. у 06:51",
  "vesti_24h": 10,
  "vesti": [
    {
      "naslov": "Najluđa utakmica Mundijala ili paravan veka?! Posle 3:3 niko na svetu više ne zna šta da misli",
      "url": "https://www.mozzartsport.com/fudbal/vesti/najlua-utakmica-mundijala-ili-paravan-veka-posle-33-niko-na-svetu-vise-ne-zna-sta-da-misli/547531",
      "izvor": "Мозарт Спорт",
      "datum": "28. 06. 2026. у 08:11",
      "slika": null
    },
    {
      "naslov": "Prokletsvo grupne faze ostaje, a odlazi čovek koji je vratio Škotsku na mapu svetskog fudbala",
      "url": "https://www.mozzartsport.com/fudbal/vesti/prokletsvo-grupne-faze-ostaje-a-odlazi-covek-koji-je-vratio-skotsku-na-mapu-svetskog-fudbala/547528",
      "izvor": "Мозарт Спорт",
      "datum": "28. 06. 2026. у 04:27",
      "slika": null
    },
    {
      "naslov": "Rijeka završava jedan od najvećih transfera: Fruk na pragu selidbe u Ligu 1",
      "url": "https://www.mozzartsport.com/fudbal/vesti/rijeka-zavrsava-jedan-od-najvecih-transfera-fruk-na-pragu-selidbe-u-ligu-1/547494",
      "izvor": "Мозарт Спорт",
      "datum": "27. 06. 2026. у 17:23",
      "slika": null
    },
    {
      "naslov": "Mundijalski pretres sa Dejom: Nisam gledao gori Brazil, Francuzi i Embape najjači, Mesi još na znanje",
      "url": "https://www.mozzartsport.com/fudbal/vesti/mundijalski-pretres-sa-dejom-nisam-gledao-gori-brazil-francuzi-i-embape-najjaci-mesi-jos-na-znanje/547463",
      "izvor": "Мозарт Спорт",
      "datum": "27. 06. 2026. у 10:23",
      "slika": null
    },
    {
      "naslov": "Kapiten fudbalera Zelenortskih Ostrva Rajan Mendeš pod istragom, optužen za silovanje",
      "url": "https://www.tanjug.rs/sport/fudbal/262240/kapiten-fudbalera-zelenortskih-ostrva-rajan-mendes-pod-istragom-optuzen-za-silovanje/vest",
      "izvor": "Танјуг",
      "datum": "27. 06. 2026. у 22:07",
      "slika": null
    },
    {
      "naslov": "Morijacu: Brazil je jedan od najboljih timova na svetu, ali imamo šansu da pobedimo",
      "url": "https://www.tanjug.rs/sport/fudbal/262207/morijacu-brazil-je-jedan-od-najboljih-timova-na-svetu-ali-imamo-sansu-da-pobedimo/vest",
      "izvor": "Танјуг",
      "datum": "27. 06. 2026. у 17:32",
      "slika": null
    },
    {
      "naslov": "Fudbaleri Australije Italijano i Leki završili učešće na Mundijalu zbog povreda",
      "url": "https://www.tanjug.rs/sport/fudbal/262205/fudbaleri-australije-italijano-i-leki-zavrsili-ucesce-na-mundijalu-zbog-povreda/vest",
      "izvor": "Танјуг",
      "datum": "27. 06. 2026. у 17:15",
      "slika": null
    },
    {
      "naslov": "Holandski fudbaler Vut Veghorst potpisao ugovor sa Tventeom",
      "url": "https://www.tanjug.rs/sport/fudbal/262182/holandski-fudbaler-vut-veghorst-potpisao-ugovor-sa-tventeom/vest",
      "izvor": "Танјуг",
      "datum": "27. 06. 2026. у 15:03",
      "slika": null
    },
    {
      "naslov": "Koković uneo novine pred Bragu – igrači bosi treniraju VIDEO",
      "url": "https://www.b92.net/sport/fudbal/srpski-fudbal/245578/kokovic-uneo-novine-pred-bragu-igraci-bosi-treniraju-video/vest",
      "izvor": "Б92 Српски фудбал",
      "datum": "27. 06. 2026. у 23:25",
      "slika": null
    },
    {
      "naslov": "Tanjga: &quot;Očekujem više od pojačanja&quot;",
      "url": "https://www.b92.net/sport/fudbal/srpski-fudbal/245557/tanjga-ocekujem-vise-od-pojacanja/vest",
      "izvor": "Б92 Српски фудбал",
      "datum": "27. 06. 2026. у 20:15",
      "slika": null
    }
  ]
}