{
  "azurirano": "2026-07-17T14:16:35.379155+00:00",
  "azurirano_sr": "17. 07. 2026. у 16:16",
  "vesti_24h": 10,
  "vesti": [
    {
      "naslov": "TRANSFERI UŽIVO (petak, 17. jul)",
      "url": "https://www.mozzartsport.com/fudbal/vesti/transferi-uzivo-petak-17-jul/549114",
      "izvor": "Мозарт Спорт",
      "datum": "17. 07. 2026. у 16:40",
      "slika": null
    },
    {
      "naslov": "Zašto kada kažete “Bugarska” pomislite na Srbiju?",
      "url": "https://www.mozzartsport.com/fudbal/vesti/zasto-kada-kazete-bugarska-pomislite-na-srbiju/549143",
      "izvor": "Мозарт Спорт",
      "datum": "17. 07. 2026. у 16:06",
      "slika": null
    },
    {
      "naslov": "Najskuplje pojačanje Lajpciga ovog leta: Naravno, francuski štoper",
      "url": "https://www.mozzartsport.com/fudbal/vesti/najskuplje-pojacanje-lajpciga-ovog-leta-naravno-francuski-stoper/549148",
      "izvor": "Мозарт Спорт",
      "datum": "17. 07. 2026. у 15:11",
      "slika": null
    },
    {
      "naslov": "Humanitarni tiket u podne: Uz Darka Anića, finalni mečevi Mundijala mirišu na dobitnih 276.000 dinara",
      "url": "https://www.mozzartsport.com/fudbal/vesti/humanitarni-tiket-u-podne-uz-darka-anica-finalni-mecevi-mundijala-mirisu-na-dobitnih-276000-dinara/549137",
      "izvor": "Мозарт Спорт",
      "datum": "17. 07. 2026. у 13:41",
      "slika": null
    },
    {
      "naslov": "Srpski arbitar Danilo Nikolić sudiće meč između fudbalera Anderlehta i Hamarbija",
      "url": "https://www.tanjug.rs/sport/fudbal/266706/srpski-arbitar-danilo-nikolic-sudice-mec-izmedu-fudbalera-anderlehta-i-hamarbija/vest",
      "izvor": "Танјуг",
      "datum": "17. 07. 2026. у 13:38",
      "slika": null
    },
    {
      "naslov": "Kazahstanski sudija Danijar Sahi sudiće meč između fudbalera Partizana i Una Štrasena",
      "url": "https://www.tanjug.rs/sport/fudbal/266690/kazahstanski-sudija-danijar-sahi-sudice-mec-izmedu-fudbalera-partizana-i-una-strasena/vest",
      "izvor": "Танјуг",
      "datum": "17. 07. 2026. у 12:50",
      "slika": null
    },
    {
      "naslov": "Ilić: Uz dužno poštovanje Zemunu, želimo da zabeležimo pobedu na startu prvenstva",
      "url": "https://www.tanjug.rs/sport/fudbal/266669/ilic-uz-duzno-postovanje-zemunu-zelimo-da-zabelezimo-pobedu-na-startu-prvenstva/vest",
      "izvor": "Танјуг",
      "datum": "17. 07. 2026. у 12:06",
      "slika": null
    },
    {
      "naslov": "Utakmice između fudbalera Crvene zvezde i Larna sude Rumun i Azerbejdžanac",
      "url": "https://www.tanjug.rs/sport/fudbal/266640/utakmice-izmedu-fudbalera-crvene-zvezde-i-larna-sude-rumun-i-azerbejdzanac/vest",
      "izvor": "Танјуг",
      "datum": "17. 07. 2026. у 10:37",
      "slika": null
    },
    {
      "naslov": "Zoran Popović za B92.sport: &quot;Ne pamtim ovakvu Superligu&quot;",
      "url": "https://www.b92.net/sport/fudbal/srpski-fudbal/250860/b92sport-intervju-zoran-popovic-golman-zeleznicara-iz-panceva/vest",
      "izvor": "Б92 Српски фудбал",
      "datum": "17. 07. 2026. у 16:00",
      "slika": null
    },
    {
      "naslov": "B92.sport intervju: Alfa i omega Železničara – put od šeste lige do Evrope",
      "url": "https://www.b92.net/sport/fudbal/srpski-fudbal/250846/b92sport-intervju-zoran-naunkovic-predsednik-fk-zeleznicar-pancevo/vest",
      "izvor": "Б92 Српски фудбал",
      "datum": "17. 07. 2026. у 12:07",
      "slika": null
    }
  ]
}