{
  "azurirano": "2026-04-27T11:23:46.052324+00:00",
  "azurirano_sr": "27. 04. 2026. у 13:23",
  "vesti_24h": 10,
  "vesti": [
    {
      "naslov": "Savić se povredio, Trabzon i bez njega napada plasman u Ligu šampiona",
      "url": "https://www.mozzartsport.com/fudbal/vesti/savic-se-povredio-trabzon-i-bez-njega-napada-plasman-u-ligu-sampiona/542339",
      "izvor": "Мозарт Спорт",
      "datum": "27. 04. 2026. у 14:07",
      "slika": null
    },
    {
      "naslov": "Simons pokidao prednji ukršteni ligament, na terenu tek 2027. godine",
      "url": "https://www.mozzartsport.com/fudbal/vesti/simons-pokidao-prednji-ukrsteni-ligament-na-terenu-tek-2027-godine/542319",
      "izvor": "Мозарт Спорт",
      "datum": "27. 04. 2026. у 06:06",
      "slika": null
    },
    {
      "naslov": "Segundo Kastiljo sedi kod kuće, manekeniše i probira poslove",
      "url": "https://www.mozzartsport.com/fudbal/vesti/segundo-kastiljo-sedi-kod-kuce-manekenise-i-probira-poslove/542255",
      "izvor": "Мозарт Спорт",
      "datum": "27. 04. 2026. у 00:58",
      "slika": null
    },
    {
      "naslov": "Prljavi, jalovi, osramoćeni i zatočeni u rešetkama od zlata: Fener štipao i ubadao Osimena - džaba!",
      "url": "https://www.mozzartsport.com/fudbal/vesti/prljavi-jalovi-osramoceni-i-zatoceni-u-resetkama-od-zlata-fener-stipao-i-ubadao-osimena-dzaba/542296",
      "izvor": "Мозарт Спорт",
      "datum": "26. 04. 2026. у 23:14",
      "slika": null
    },
    {
      "naslov": "Fudbaler Totenhema Ćavi Simons pokidao prednje ukrštene ligamente kolena",
      "url": "https://www.tanjug.rs/sport/fudbal/247747/fudbaler-totenhema-cavi-simons-pokidao-prednje-ukrstene-ligamente-kolena/vest",
      "izvor": "Танјуг",
      "datum": "27. 04. 2026. у 11:14",
      "slika": null
    },
    {
      "naslov": "\"Nula\" fudbalera Milana i Juventusa na San Siru",
      "url": "https://www.tanjug.rs/sport/fudbal/247679/nula-fudbalera-milana-i-juventusa-na-san-siru/vest",
      "izvor": "Танјуг",
      "datum": "26. 04. 2026. у 23:04",
      "slika": null
    },
    {
      "naslov": "Remi fudbalera Vojvodine i Železničara u Novom Sadu",
      "url": "https://www.tanjug.rs/sport/fudbal/247670/remi-fudbalera-vojvodine-i-zeleznicara-u-novom-sadu/vest",
      "izvor": "Танјуг",
      "datum": "26. 04. 2026. у 22:16",
      "slika": null
    },
    {
      "naslov": "Zvezdan Terzić: Titula osvojena na najlepši mogući način, želimo i šestu duplu krunu u nizu",
      "url": "https://www.tanjug.rs/sport/fudbal/247668/zvezdan-terzic-titula-osvojena-na-najlepsi-moguci-nacin-zelimo-i-sestu-duplu-krunu-u-nizu/vest",
      "izvor": "Танјуг",
      "datum": "26. 04. 2026. у 22:08",
      "slika": null
    },
    {
      "naslov": "Zvezdin najgori bolji od Partizanovog najboljeg",
      "url": "https://www.b92.net/sport/fudbal/srpski-fudbal/228438/ocene-fudbalera-zvezde-i-partizana-posle-179-vecitog-derbija/vest",
      "izvor": "Б92 Српски фудбал",
      "datum": "27. 04. 2026. у 12:51",
      "slika": null
    },
    {
      "naslov": "Istorijska razlika u &quot;večitim&quot; derbijima",
      "url": "https://www.b92.net/sport/fudbal/srpski-fudbal/228425/crvena-zvezda-ima-25-pobeda-vise-u-derbijima-od-partizana/vest",
      "izvor": "Б92 Српски фудбал",
      "datum": "27. 04. 2026. у 12:12",
      "slika": null
    }
  ]
}